tests/__init__.py
tests/test_uipcalc.py
uipcalc/__init__.py
uipcalc-0.3.3.dist-info/DESCRIPTION.rst
uipcalc-0.3.3.dist-info/METADATA
uipcalc-0.3.3.dist-info/RECORD
uipcalc-0.3.3.dist-info/WHEEL
uipcalc-0.3.3.dist-info/entry_points.txt
uipcalc-0.3.3.dist-info/metadata.json
uipcalc-0.3.3.dist-info/top_level.txt
