Metadata-Version: 2.0
Name: uipcalc
Version: 0.3.3
Summary: Universal (IPv4/IPv6) IP address and netmask calculator
Home-page: https://bitbucket.org/asenci/uipcalc/
Author: Andre Sencioles
Author-email: asenci@gmail.com
License: ISC License
Keywords: ip ipv4 ipv6 net subnet network netmask calc calculator
Platform: any
Classifier: Development Status :: 5 - Production/Stable
Classifier: Environment :: Console
Classifier: Intended Audience :: System Administrators
Classifier: License :: OSI Approved :: ISC License (ISCL)
Classifier: Natural Language :: English
Classifier: Operating System :: OS Independent
Classifier: Programming Language :: Python
Classifier: Programming Language :: Python :: 2
Classifier: Programming Language :: Python :: 2.7
Classifier: Programming Language :: Python :: 3
Classifier: Programming Language :: Python :: 3.4
Classifier: Programming Language :: Python :: 3.5
Classifier: Programming Language :: Python :: Implementation :: CPython
Classifier: Topic :: System :: Networking
Classifier: Topic :: Utilities
Requires-Dist: six
Requires-Dist: ipaddress; python_version<"3.3"
Provides-Extra: testing
Requires-Dist: nose; extra == 'testing'
Requires-Dist: tox; extra == 'testing'
